AUTHORS
ChangeLog
LICENSE
MANIFEST.in
README.rst
requirements.txt
setup.cfg
setup.py
leonardo_theme_bootswatch/__init__.py
leonardo_theme_bootswatch.egg-info/PKG-INFO
leonardo_theme_bootswatch.egg-info/SOURCES.txt
leonardo_theme_bootswatch.egg-info/dependency_links.txt
leonardo_theme_bootswatch.egg-info/not-zip-safe
leonardo_theme_bootswatch.egg-info/pbr.json
leonardo_theme_bootswatch.egg-info/requires.txt
leonardo_theme_bootswatch.egg-info/top_level.txt
leonardo_theme_bootswatch/static/fonts/glyphicons-halflings-regular.eot
leonardo_theme_bootswatch/static/fonts/glyphicons-halflings-regular.svg
leonardo_theme_bootswatch/static/fonts/glyphicons-halflings-regular.ttf
leonardo_theme_bootswatch/static/fonts/glyphicons-halflings-regular.woff
leonardo_theme_bootswatch/static/themes/bootswatch/_styles.scss
leonardo_theme_bootswatch/static/themes/bootswatch/cerulean/_styles.scss
leonardo_theme_bootswatch/static/themes/bootswatch/cerulean/_variables.scss
leonardo_theme_bootswatch/static/themes/bootswatch/cerulean/scheme.scss
leonardo_theme_bootswatch/static/themes/bootswatch/cosmo/_styles.scss
leonardo_theme_bootswatch/static/themes/bootswatch/cosmo/_variables.scss
leonardo_theme_bootswatch/static/themes/bootswatch/cosmo/scheme.scss
leonardo_theme_bootswatch/static/themes/bootswatch/custom/_styles.scss
leonardo_theme_bootswatch/static/themes/bootswatch/custom/_variables.scss
leonardo_theme_bootswatch/static/themes/bootswatch/custom/scheme.scss
leonardo_theme_bootswatch/static/themes/bootswatch/cyborg/_styles.scss
leonardo_theme_bootswatch/static/themes/bootswatch/cyborg/_variables.scss
leonardo_theme_bootswatch/static/themes/bootswatch/cyborg/scheme.scss
leonardo_theme_bootswatch/static/themes/bootswatch/darkly/_styles.scss
leonardo_theme_bootswatch/static/themes/bootswatch/darkly/_variables.scss
leonardo_theme_bootswatch/static/themes/bootswatch/darkly/scheme.scss
leonardo_theme_bootswatch/static/themes/bootswatch/flatly/_styles.scss
leonardo_theme_bootswatch/static/themes/bootswatch/flatly/_variables.scss
leonardo_theme_bootswatch/static/themes/bootswatch/flatly/scheme.scss
leonardo_theme_bootswatch/static/themes/bootswatch/fonts/glyphicons-halflings-regular.eot
leonardo_theme_bootswatch/static/themes/bootswatch/fonts/glyphicons-halflings-regular.ttf
