Metadata-Version: 1.1
Name: leonardo-theme-bootswatch
Version: 2016.2.0
Summary: Bootswatch theme for Leonardo
Home-page: https://github.com/django-leonardo/leonardo-theme-bootswatch.git
Author: Ales Komarek, Michael Kuty
Author-email: mail@newt.cz
License: UNKNOWN
Platform: UNKNOWN
Classifier: Development Status :: 5 - Production/Stable
Classifier: Framework :: Django
Classifier: Intended Audience :: Developers
Classifier: License :: OSI Approved :: BSD License
Classifier: Operating System :: OS Independent
Classifier: Programming Language :: Python
Classifier: Programming Language :: Python :: 2.6
Classifier: Programming Language :: Python :: 2.7
Classifier: Programming Language :: Python :: 3
Classifier: Programming Language :: Python :: 3.3
Classifier: Programming Language :: Python :: 3.4
Classifier: Topic :: Software Development
Classifier: Topic :: Software Development :: Libraries :: Application Frameworks
